{
  "schemaVersion": "0.1.0",
  "packetId": "review:f2898a08-1412-5f0e-a164-ea1230bb8e04",
  "episodeId": "f2898a08-1412-5f0e-a164-ea1230bb8e04",
  "status": "awaiting_human_review",
  "createdAt": "2026-07-21T11:08:43Z",
  "sourceFamily": "conformance_calculus",
  "qualityTierAtQueue": "Q2_formally_verified",
  "requestedReview": "semantically_reviewed",
  "humanReviewLabels": [],
  "checklist": [
    "Statement fidelity to the mathematical claim",
    "Witness / certificate interpretation correctness",
    "No overclaim of unbounded theorems from bounded evidence",
    "Contamination / public-library novelty judgment"
  ],
  "artifactRefs": [
    "evidence/conformance/symbolic_calculus/calculus_ode_y_eq_x/bundle"
  ],
  "notes": "Unlabeled queue item. Do NOT count as Q3 until a human adds humanReviewLabels including semantically_reviewed.",
  "acceptanceInfluence": false
}
